{
  "date": "2026-03-10",
  "time": "2026-03-10 10:31:04",
  "mood": "🚀 风险偏好回升",
  "sections": {
    "macro": {
      "title": "🌍 宏观风向标",
      "summary": "美股整体显著走强，A股表现显著偏强，跨市场风险偏好维持风险偏好回升。"
    },
    "us": {
      "title": "🇺🇸 美股聚焦",
      "items": [
        "道指 (DJI): 47740.8 (▲ +0.78%)",
        "标普500 (SPX): 6795.99 (▲ +1.44%)",
        "纳斯达克100 (NDQ): 22695.95 (▲ +2.31%)"
      ],
      "summary": "美股三大指数呈现显著波动，短线仍由利率预期与AI成长叙事共同定价。"
    },
    "cn": {
      "title": "🇨🇳 A股透视",
      "items": [
        "上证指数: 4109.40 (▲ +0.31%)",
        "深证成指: 14284.99 (▲ +1.55%)",
        "创业板指: 3290.24 (▲ +2.55%)"
      ],
      "summary": "A股三大指数今日显著上行，风格切换仍围绕权重与成长之间展开。"
    },
    "commodities": {
      "title": "⛽️💰 大宗商品",
      "items": [
        "WTI 原油: 85.89 (▼ -2.26%)",
        "布伦特原油: 89.17 (▼ -3.60%)",
        "黄金 (XAUUSD): 5180.94 (▲ +0.54%)",
        "白银 (XAGUSD): 89.623 (▲ +2.43%)"
      ],
      "summary": "原油表现显著偏弱，贵金属继续受美元与实际利率预期影响。"
    },
    "strategy": {
      "title": "💡 策略综述与明日展望",
      "summary": "🚀 风险偏好回升：优先跟踪数据验证，避免在显著波动阶段做情绪化追涨杀跌。"
    }
  }
}